cellprofiler/__init__.py
cellprofiler/__main__.py
cellprofiler/_version.py
cellprofiler/knime_bridge.py
cellprofiler/misc.py
cellprofiler/data/examples/ExampleFly/ExampleFly.cppipe
cellprofiler/data/examples/ExampleFly/images/01_POS002_D.TIF
cellprofiler/data/examples/ExampleFly/images/01_POS002_F.TIF
cellprofiler/data/examples/ExampleFly/images/01_POS002_R.TIF
cellprofiler/data/examples/ExampleFly/images/01_POS076_D.TIF
cellprofiler/data/examples/ExampleFly/images/01_POS076_F.TIF
cellprofiler/data/examples/ExampleFly/images/01_POS076_R.TIF
cellprofiler/data/examples/ExampleFly/images/01_POS218_D.TIF
cellprofiler/data/examples/ExampleFly/images/01_POS218_F.TIF
cellprofiler/data/examples/ExampleFly/images/01_POS218_R.TIF
cellprofiler/data/help/display_image_tools.rst
cellprofiler/data/help/display_interactive_navigation.rst
cellprofiler/data/help/display_menu_bar.rst
cellprofiler/data/help/legacy_matlab_image.rst
cellprofiler/data/help/navigation_edit_menu.rst
cellprofiler/data/help/navigation_file_menu.rst
cellprofiler/data/help/navigation_test_menu.rst
cellprofiler/data/help/navigation_window_menu.rst
cellprofiler/data/help/other_3d_identify.rst
cellprofiler/data/help/other_batch.rst
cellprofiler/data/help/other_logging.rst
cellprofiler/data/help/other_omero.rst
cellprofiler/data/help/other_plugins.rst
cellprofiler/data/help/other_shell.rst
cellprofiler/data/help/other_troubleshooting.rst
cellprofiler/data/help/other_widget_inspector.rst
cellprofiler/data/help/output_measurements.rst
cellprofiler/data/help/output_plateviewer.rst
cellprofiler/data/help/output_spreadsheets.rst
cellprofiler/data/help/pipelines_building.rst
cellprofiler/data/help/pipelines_running.rst
cellprofiler/data/help/projects_configure_images.rst
cellprofiler/data/help/projects_image_ordering.rst
cellprofiler/data/help/projects_image_sequences.rst
cellprofiler/data/help/projects_introduction.rst
cellprofiler/data/help/projects_selecting_images.rst
cellprofiler/data/help/why_use_cellprofiler.rst
cellprofiler_nightly-5.0.0.dev340.dist-info/licenses/LICENSE
cellprofiler_nightly-5.0.0.dev340.dist-info/METADATA
cellprofiler_nightly-5.0.0.dev340.dist-info/WHEEL
cellprofiler_nightly-5.0.0.dev340.dist-info/entry_points.txt
cellprofiler_nightly-5.0.0.dev340.dist-info/top_level.txt
cellprofiler_nightly-5.0.0.dev340.dist-info/RECORD
